{
	"configurations" : 
	[
		{
			"directories" : 
			[
				{
					"build" : ".",
					"childIndexes" : 
					[
						1
					],
					"jsonFile" : "directory-.-Debug-d0094a50bb2071803777.json",
					"minimumCMakeVersion" : 
					{
						"string" : "3.8"
					},
					"projectIndex" : 0,
					"source" : "."
				},
				{
					"build" : "DynamicPartitionAllocation",
					"jsonFile" : "directory-DynamicPartitionAllocation-Debug-f0464da52fd27ab73b3b.json",
					"minimumCMakeVersion" : 
					{
						"string" : "3.8"
					},
					"parentIndex" : 0,
					"projectIndex" : 0,
					"source" : "DynamicPartitionAllocation",
					"targetIndexes" : 
					[
						0
					]
				}
			],
			"name" : "Debug",
			"projects" : 
			[
				{
					"directoryIndexes" : 
					[
						0,
						1
					],
					"name" : "DynamicPartitionAllocation",
					"targetIndexes" : 
					[
						0
					]
				}
			],
			"targets" : 
			[
				{
					"directoryIndex" : 1,
					"id" : "DynamicPartitionAllocation::@2b66c6b0baa39f396ac5",
					"jsonFile" : "target-DynamicPartitionAllocation-Debug-8b41a2cefc5f0c91d4cb.json",
					"name" : "DynamicPartitionAllocation",
					"projectIndex" : 0
				}
			]
		}
	],
	"kind" : "codemodel",
	"paths" : 
	{
		"build" : "D:/code/os/9/DynamicPartitionAllocation/cmake-build-debug",
		"source" : "D:/code/os/9/DynamicPartitionAllocation"
	},
	"version" : 
	{
		"major" : 2,
		"minor" : 5
	}
}
